{
	"configurations" : 
	[
		{
			"directories" : 
			[
				{
					"build" : ".",
					"childIndexes" : 
					[
						1
					],
					"hasInstallRule" : true,
					"jsonFile" : "directory-.-Debug-d0094a50bb2071803777.json",
					"minimumCMakeVersion" : 
					{
						"string" : "3.5"
					},
					"projectIndex" : 0,
					"source" : ".",
					"targetIndexes" : 
					[
						0,
						4,
						5,
						10
					]
				},
				{
					"build" : "googletest",
					"childIndexes" : 
					[
						2
					],
					"hasInstallRule" : true,
					"jsonFile" : "directory-googletest-Debug-294c64d4885f2a55f3f7.json",
					"minimumCMakeVersion" : 
					{
						"string" : "3.5"
					},
					"parentIndex" : 0,
					"projectIndex" : 1,
					"source" : "googletest",
					"targetIndexes" : 
					[
						1
					]
				},
				{
					"build" : "googletest/googlemock",
					"childIndexes" : 
					[
						3
					],
					"hasInstallRule" : true,
					"jsonFile" : "directory-googletest.googlemock-Debug-b289e34a29f2ddf193d9.json",
					"minimumCMakeVersion" : 
					{
						"string" : "3.5"
					},
					"parentIndex" : 1,
					"projectIndex" : 2,
					"source" : "googletest/googlemock",
					"targetIndexes" : 
					[
						2,
						6,
						7
					]
				},
				{
					"build" : "googletest/googletest",
					"hasInstallRule" : true,
					"jsonFile" : "directory-googletest.googletest-Debug-a7ee842a93e7e2d8df01.json",
					"minimumCMakeVersion" : 
					{
						"string" : "3.5"
					},
					"parentIndex" : 2,
					"projectIndex" : 3,
					"source" : "googletest/googletest",
					"targetIndexes" : 
					[
						3,
						8,
						9
					]
				}
			],
			"name" : "Debug",
			"projects" : 
			[
				{
					"childIndexes" : 
					[
						1
					],
					"directoryIndexes" : 
					[
						0
					],
					"name" : "HelloApp",
					"targetIndexes" : 
					[
						0,
						4,
						5,
						10
					]
				},
				{
					"childIndexes" : 
					[
						2
					],
					"directoryIndexes" : 
					[
						1
					],
					"name" : "googletest-distribution",
					"parentIndex" : 0,
					"targetIndexes" : 
					[
						1
					]
				},
				{
					"childIndexes" : 
					[
						3
					],
					"directoryIndexes" : 
					[
						2
					],
					"name" : "gmock",
					"parentIndex" : 1,
					"targetIndexes" : 
					[
						2,
						6,
						7
					]
				},
				{
					"directoryIndexes" : 
					[
						3
					],
					"name" : "gtest",
					"parentIndex" : 2,
					"targetIndexes" : 
					[
						3,
						8,
						9
					]
				}
			],
			"targets" : 
			[
				{
					"directoryIndex" : 0,
					"id" : "ALL_BUILD::@6890427a1f51a3e7e1df",
					"jsonFile" : "target-ALL_BUILD-Debug-24b720d9f0ce0dab85e2.json",
					"name" : "ALL_BUILD",
					"projectIndex" : 0
				},
				{
					"directoryIndex" : 1,
					"id" : "ALL_BUILD::@b3026ea3adfb7c2366ee",
					"jsonFile" : "target-ALL_BUILD-Debug-648c03c9659bcfdc434f.json",
					"name" : "ALL_BUILD",
					"projectIndex" : 1
				},
				{
					"directoryIndex" : 2,
					"id" : "ALL_BUILD::@d68da25237a7ca2351af",
					"jsonFile" : "target-ALL_BUILD-Debug-756aac6da4b6e609e80f.json",
					"name" : "ALL_BUILD",
					"projectIndex" : 2
				},
				{
					"directoryIndex" : 3,
					"id" : "ALL_BUILD::@f95b5c00bd49b3b4698d",
					"jsonFile" : "target-ALL_BUILD-Debug-0cf07ca160f3d4a22d90.json",
					"name" : "ALL_BUILD",
					"projectIndex" : 3
				},
				{
					"directoryIndex" : 0,
					"id" : "HelloAppBinary::@6890427a1f51a3e7e1df",
					"jsonFile" : "target-HelloAppBinary-Debug-591b8a50e64faf7e635c.json",
					"name" : "HelloAppBinary",
					"projectIndex" : 0
				},
				{
					"directoryIndex" : 0,
					"id" : "ZERO_CHECK::@6890427a1f51a3e7e1df",
					"jsonFile" : "target-ZERO_CHECK-Debug-eabf0dedd0c7dceea010.json",
					"name" : "ZERO_CHECK",
					"projectIndex" : 0
				},
				{
					"directoryIndex" : 2,
					"id" : "gmock::@d68da25237a7ca2351af",
					"jsonFile" : "target-gmock-Debug-54efaa1c8034b35ab9c4.json",
					"name" : "gmock",
					"projectIndex" : 2
				},
				{
					"directoryIndex" : 2,
					"id" : "gmock_main::@d68da25237a7ca2351af",
					"jsonFile" : "target-gmock_main-Debug-db8f9edcaa4e3bfad083.json",
					"name" : "gmock_main",
					"projectIndex" : 2
				},
				{
					"directoryIndex" : 3,
					"id" : "gtest::@f95b5c00bd49b3b4698d",
					"jsonFile" : "target-gtest-Debug-249fe59b6f10ac72f755.json",
					"name" : "gtest",
					"projectIndex" : 3
				},
				{
					"directoryIndex" : 3,
					"id" : "gtest_main::@f95b5c00bd49b3b4698d",
					"jsonFile" : "target-gtest_main-Debug-b45bbda681d79ece255f.json",
					"name" : "gtest_main",
					"projectIndex" : 3
				},
				{
					"directoryIndex" : 0,
					"id" : "my_tests::@6890427a1f51a3e7e1df",
					"jsonFile" : "target-my_tests-Debug-552c6f09ada79a285647.json",
					"name" : "my_tests",
					"projectIndex" : 0
				}
			]
		},
		{
			"directories" : 
			[
				{
					"build" : ".",
					"childIndexes" : 
					[
						1
					],
					"hasInstallRule" : true,
					"jsonFile" : "directory-.-Release-d0094a50bb2071803777.json",
					"minimumCMakeVersion" : 
					{
						"string" : "3.5"
					},
					"projectIndex" : 0,
					"source" : ".",
					"targetIndexes" : 
					[
						0,
						4,
						5,
						10
					]
				},
				{
					"build" : "googletest",
					"childIndexes" : 
					[
						2
					],
					"hasInstallRule" : true,
					"jsonFile" : "directory-googletest-Release-294c64d4885f2a55f3f7.json",
					"minimumCMakeVersion" : 
					{
						"string" : "3.5"
					},
					"parentIndex" : 0,
					"projectIndex" : 1,
					"source" : "googletest",
					"targetIndexes" : 
					[
						1
					]
				},
				{
					"build" : "googletest/googlemock",
					"childIndexes" : 
					[
						3
					],
					"hasInstallRule" : true,
					"jsonFile" : "directory-googletest.googlemock-Release-e5e42950f07443fc2d4d.json",
					"minimumCMakeVersion" : 
					{
						"string" : "3.5"
					},
					"parentIndex" : 1,
					"projectIndex" : 2,
					"source" : "googletest/googlemock",
					"targetIndexes" : 
					[
						2,
						6,
						7
					]
				},
				{
					"build" : "googletest/googletest",
					"hasInstallRule" : true,
					"jsonFile" : "directory-googletest.googletest-Release-3f9cc1fc1a8e9c793213.json",
					"minimumCMakeVersion" : 
					{
						"string" : "3.5"
					},
					"parentIndex" : 2,
					"projectIndex" : 3,
					"source" : "googletest/googletest",
					"targetIndexes" : 
					[
						3,
						8,
						9
					]
				}
			],
			"name" : "Release",
			"projects" : 
			[
				{
					"childIndexes" : 
					[
						1
					],
					"directoryIndexes" : 
					[
						0
					],
					"name" : "HelloApp",
					"targetIndexes" : 
					[
						0,
						4,
						5,
						10
					]
				},
				{
					"childIndexes" : 
					[
						2
					],
					"directoryIndexes" : 
					[
						1
					],
					"name" : "googletest-distribution",
					"parentIndex" : 0,
					"targetIndexes" : 
					[
						1
					]
				},
				{
					"childIndexes" : 
					[
						3
					],
					"directoryIndexes" : 
					[
						2
					],
					"name" : "gmock",
					"parentIndex" : 1,
					"targetIndexes" : 
					[
						2,
						6,
						7
					]
				},
				{
					"directoryIndexes" : 
					[
						3
					],
					"name" : "gtest",
					"parentIndex" : 2,
					"targetIndexes" : 
					[
						3,
						8,
						9
					]
				}
			],
			"targets" : 
			[
				{
					"directoryIndex" : 0,
					"id" : "ALL_BUILD::@6890427a1f51a3e7e1df",
					"jsonFile" : "target-ALL_BUILD-Release-24b720d9f0ce0dab85e2.json",
					"name" : "ALL_BUILD",
					"projectIndex" : 0
				},
				{
					"directoryIndex" : 1,
					"id" : "ALL_BUILD::@b3026ea3adfb7c2366ee",
					"jsonFile" : "target-ALL_BUILD-Release-648c03c9659bcfdc434f.json",
					"name" : "ALL_BUILD",
					"projectIndex" : 1
				},
				{
					"directoryIndex" : 2,
					"id" : "ALL_BUILD::@d68da25237a7ca2351af",
					"jsonFile" : "target-ALL_BUILD-Release-756aac6da4b6e609e80f.json",
					"name" : "ALL_BUILD",
					"projectIndex" : 2
				},
				{
					"directoryIndex" : 3,
					"id" : "ALL_BUILD::@f95b5c00bd49b3b4698d",
					"jsonFile" : "target-ALL_BUILD-Release-0cf07ca160f3d4a22d90.json",
					"name" : "ALL_BUILD",
					"projectIndex" : 3
				},
				{
					"directoryIndex" : 0,
					"id" : "HelloAppBinary::@6890427a1f51a3e7e1df",
					"jsonFile" : "target-HelloAppBinary-Release-66acebd4f19c2c12ef4a.json",
					"name" : "HelloAppBinary",
					"projectIndex" : 0
				},
				{
					"directoryIndex" : 0,
					"id" : "ZERO_CHECK::@6890427a1f51a3e7e1df",
					"jsonFile" : "target-ZERO_CHECK-Release-eabf0dedd0c7dceea010.json",
					"name" : "ZERO_CHECK",
					"projectIndex" : 0
				},
				{
					"directoryIndex" : 2,
					"id" : "gmock::@d68da25237a7ca2351af",
					"jsonFile" : "target-gmock-Release-0f28622c4a6b698de803.json",
					"name" : "gmock",
					"projectIndex" : 2
				},
				{
					"directoryIndex" : 2,
					"id" : "gmock_main::@d68da25237a7ca2351af",
					"jsonFile" : "target-gmock_main-Release-9040e704620d181c3e31.json",
					"name" : "gmock_main",
					"projectIndex" : 2
				},
				{
					"directoryIndex" : 3,
					"id" : "gtest::@f95b5c00bd49b3b4698d",
					"jsonFile" : "target-gtest-Release-a18198ac66b85b81b611.json",
					"name" : "gtest",
					"projectIndex" : 3
				},
				{
					"directoryIndex" : 3,
					"id" : "gtest_main::@f95b5c00bd49b3b4698d",
					"jsonFile" : "target-gtest_main-Release-026e2af12edcf8154c66.json",
					"name" : "gtest_main",
					"projectIndex" : 3
				},
				{
					"directoryIndex" : 0,
					"id" : "my_tests::@6890427a1f51a3e7e1df",
					"jsonFile" : "target-my_tests-Release-6bb458b399627bf46c97.json",
					"name" : "my_tests",
					"projectIndex" : 0
				}
			]
		},
		{
			"directories" : 
			[
				{
					"build" : ".",
					"childIndexes" : 
					[
						1
					],
					"hasInstallRule" : true,
					"jsonFile" : "directory-.-MinSizeRel-d0094a50bb2071803777.json",
					"minimumCMakeVersion" : 
					{
						"string" : "3.5"
					},
					"projectIndex" : 0,
					"source" : ".",
					"targetIndexes" : 
					[
						0,
						4,
						5,
						10
					]
				},
				{
					"build" : "googletest",
					"childIndexes" : 
					[
						2
					],
					"hasInstallRule" : true,
					"jsonFile" : "directory-googletest-MinSizeRel-294c64d4885f2a55f3f7.json",
					"minimumCMakeVersion" : 
					{
						"string" : "3.5"
					},
					"parentIndex" : 0,
					"projectIndex" : 1,
					"source" : "googletest",
					"targetIndexes" : 
					[
						1
					]
				},
				{
					"build" : "googletest/googlemock",
					"childIndexes" : 
					[
						3
					],
					"hasInstallRule" : true,
					"jsonFile" : "directory-googletest.googlemock-MinSizeRel-6594089df5bbeafd3a73.json",
					"minimumCMakeVersion" : 
					{
						"string" : "3.5"
					},
					"parentIndex" : 1,
					"projectIndex" : 2,
					"source" : "googletest/googlemock",
					"targetIndexes" : 
					[
						2,
						6,
						7
					]
				},
				{
					"build" : "googletest/googletest",
					"hasInstallRule" : true,
					"jsonFile" : "directory-googletest.googletest-MinSizeRel-8c60822fb215445a3d54.json",
					"minimumCMakeVersion" : 
					{
						"string" : "3.5"
					},
					"parentIndex" : 2,
					"projectIndex" : 3,
					"source" : "googletest/googletest",
					"targetIndexes" : 
					[
						3,
						8,
						9
					]
				}
			],
			"name" : "MinSizeRel",
			"projects" : 
			[
				{
					"childIndexes" : 
					[
						1
					],
					"directoryIndexes" : 
					[
						0
					],
					"name" : "HelloApp",
					"targetIndexes" : 
					[
						0,
						4,
						5,
						10
					]
				},
				{
					"childIndexes" : 
					[
						2
					],
					"directoryIndexes" : 
					[
						1
					],
					"name" : "googletest-distribution",
					"parentIndex" : 0,
					"targetIndexes" : 
					[
						1
					]
				},
				{
					"childIndexes" : 
					[
						3
					],
					"directoryIndexes" : 
					[
						2
					],
					"name" : "gmock",
					"parentIndex" : 1,
					"targetIndexes" : 
					[
						2,
						6,
						7
					]
				},
				{
					"directoryIndexes" : 
					[
						3
					],
					"name" : "gtest",
					"parentIndex" : 2,
					"targetIndexes" : 
					[
						3,
						8,
						9
					]
				}
			],
			"targets" : 
			[
				{
					"directoryIndex" : 0,
					"id" : "ALL_BUILD::@6890427a1f51a3e7e1df",
					"jsonFile" : "target-ALL_BUILD-MinSizeRel-24b720d9f0ce0dab85e2.json",
					"name" : "ALL_BUILD",
					"projectIndex" : 0
				},
				{
					"directoryIndex" : 1,
					"id" : "ALL_BUILD::@b3026ea3adfb7c2366ee",
					"jsonFile" : "target-ALL_BUILD-MinSizeRel-648c03c9659bcfdc434f.json",
					"name" : "ALL_BUILD",
					"projectIndex" : 1
				},
				{
					"directoryIndex" : 2,
					"id" : "ALL_BUILD::@d68da25237a7ca2351af",
					"jsonFile" : "target-ALL_BUILD-MinSizeRel-756aac6da4b6e609e80f.json",
					"name" : "ALL_BUILD",
					"projectIndex" : 2
				},
				{
					"directoryIndex" : 3,
					"id" : "ALL_BUILD::@f95b5c00bd49b3b4698d",
					"jsonFile" : "target-ALL_BUILD-MinSizeRel-0cf07ca160f3d4a22d90.json",
					"name" : "ALL_BUILD",
					"projectIndex" : 3
				},
				{
					"directoryIndex" : 0,
					"id" : "HelloAppBinary::@6890427a1f51a3e7e1df",
					"jsonFile" : "target-HelloAppBinary-MinSizeRel-ab2486cd60cecee789f4.json",
					"name" : "HelloAppBinary",
					"projectIndex" : 0
				},
				{
					"directoryIndex" : 0,
					"id" : "ZERO_CHECK::@6890427a1f51a3e7e1df",
					"jsonFile" : "target-ZERO_CHECK-MinSizeRel-eabf0dedd0c7dceea010.json",
					"name" : "ZERO_CHECK",
					"projectIndex" : 0
				},
				{
					"directoryIndex" : 2,
					"id" : "gmock::@d68da25237a7ca2351af",
					"jsonFile" : "target-gmock-MinSizeRel-df9b9ca494883fb2bb72.json",
					"name" : "gmock",
					"projectIndex" : 2
				},
				{
					"directoryIndex" : 2,
					"id" : "gmock_main::@d68da25237a7ca2351af",
					"jsonFile" : "target-gmock_main-MinSizeRel-4ecd9313a099fa50bc41.json",
					"name" : "gmock_main",
					"projectIndex" : 2
				},
				{
					"directoryIndex" : 3,
					"id" : "gtest::@f95b5c00bd49b3b4698d",
					"jsonFile" : "target-gtest-MinSizeRel-3a6f200ac6b48ab08579.json",
					"name" : "gtest",
					"projectIndex" : 3
				},
				{
					"directoryIndex" : 3,
					"id" : "gtest_main::@f95b5c00bd49b3b4698d",
					"jsonFile" : "target-gtest_main-MinSizeRel-eefbebd4d70a7e08e170.json",
					"name" : "gtest_main",
					"projectIndex" : 3
				},
				{
					"directoryIndex" : 0,
					"id" : "my_tests::@6890427a1f51a3e7e1df",
					"jsonFile" : "target-my_tests-MinSizeRel-77d7eb528c94b04828b2.json",
					"name" : "my_tests",
					"projectIndex" : 0
				}
			]
		},
		{
			"directories" : 
			[
				{
					"build" : ".",
					"childIndexes" : 
					[
						1
					],
					"hasInstallRule" : true,
					"jsonFile" : "directory-.-RelWithDebInfo-d0094a50bb2071803777.json",
					"minimumCMakeVersion" : 
					{
						"string" : "3.5"
					},
					"projectIndex" : 0,
					"source" : ".",
					"targetIndexes" : 
					[
						0,
						4,
						5,
						10
					]
				},
				{
					"build" : "googletest",
					"childIndexes" : 
					[
						2
					],
					"hasInstallRule" : true,
					"jsonFile" : "directory-googletest-RelWithDebInfo-294c64d4885f2a55f3f7.json",
					"minimumCMakeVersion" : 
					{
						"string" : "3.5"
					},
					"parentIndex" : 0,
					"projectIndex" : 1,
					"source" : "googletest",
					"targetIndexes" : 
					[
						1
					]
				},
				{
					"build" : "googletest/googlemock",
					"childIndexes" : 
					[
						3
					],
					"hasInstallRule" : true,
					"jsonFile" : "directory-googletest.googlemock-RelWithDebInfo-0acf54d0fe9947e46f46.json",
					"minimumCMakeVersion" : 
					{
						"string" : "3.5"
					},
					"parentIndex" : 1,
					"projectIndex" : 2,
					"source" : "googletest/googlemock",
					"targetIndexes" : 
					[
						2,
						6,
						7
					]
				},
				{
					"build" : "googletest/googletest",
					"hasInstallRule" : true,
					"jsonFile" : "directory-googletest.googletest-RelWithDebInfo-e693f17bcf45cb6848bc.json",
					"minimumCMakeVersion" : 
					{
						"string" : "3.5"
					},
					"parentIndex" : 2,
					"projectIndex" : 3,
					"source" : "googletest/googletest",
					"targetIndexes" : 
					[
						3,
						8,
						9
					]
				}
			],
			"name" : "RelWithDebInfo",
			"projects" : 
			[
				{
					"childIndexes" : 
					[
						1
					],
					"directoryIndexes" : 
					[
						0
					],
					"name" : "HelloApp",
					"targetIndexes" : 
					[
						0,
						4,
						5,
						10
					]
				},
				{
					"childIndexes" : 
					[
						2
					],
					"directoryIndexes" : 
					[
						1
					],
					"name" : "googletest-distribution",
					"parentIndex" : 0,
					"targetIndexes" : 
					[
						1
					]
				},
				{
					"childIndexes" : 
					[
						3
					],
					"directoryIndexes" : 
					[
						2
					],
					"name" : "gmock",
					"parentIndex" : 1,
					"targetIndexes" : 
					[
						2,
						6,
						7
					]
				},
				{
					"directoryIndexes" : 
					[
						3
					],
					"name" : "gtest",
					"parentIndex" : 2,
					"targetIndexes" : 
					[
						3,
						8,
						9
					]
				}
			],
			"targets" : 
			[
				{
					"directoryIndex" : 0,
					"id" : "ALL_BUILD::@6890427a1f51a3e7e1df",
					"jsonFile" : "target-ALL_BUILD-RelWithDebInfo-24b720d9f0ce0dab85e2.json",
					"name" : "ALL_BUILD",
					"projectIndex" : 0
				},
				{
					"directoryIndex" : 1,
					"id" : "ALL_BUILD::@b3026ea3adfb7c2366ee",
					"jsonFile" : "target-ALL_BUILD-RelWithDebInfo-648c03c9659bcfdc434f.json",
					"name" : "ALL_BUILD",
					"projectIndex" : 1
				},
				{
					"directoryIndex" : 2,
					"id" : "ALL_BUILD::@d68da25237a7ca2351af",
					"jsonFile" : "target-ALL_BUILD-RelWithDebInfo-756aac6da4b6e609e80f.json",
					"name" : "ALL_BUILD",
					"projectIndex" : 2
				},
				{
					"directoryIndex" : 3,
					"id" : "ALL_BUILD::@f95b5c00bd49b3b4698d",
					"jsonFile" : "target-ALL_BUILD-RelWithDebInfo-0cf07ca160f3d4a22d90.json",
					"name" : "ALL_BUILD",
					"projectIndex" : 3
				},
				{
					"directoryIndex" : 0,
					"id" : "HelloAppBinary::@6890427a1f51a3e7e1df",
					"jsonFile" : "target-HelloAppBinary-RelWithDebInfo-3ab80a03d66dbb649840.json",
					"name" : "HelloAppBinary",
					"projectIndex" : 0
				},
				{
					"directoryIndex" : 0,
					"id" : "ZERO_CHECK::@6890427a1f51a3e7e1df",
					"jsonFile" : "target-ZERO_CHECK-RelWithDebInfo-eabf0dedd0c7dceea010.json",
					"name" : "ZERO_CHECK",
					"projectIndex" : 0
				},
				{
					"directoryIndex" : 2,
					"id" : "gmock::@d68da25237a7ca2351af",
					"jsonFile" : "target-gmock-RelWithDebInfo-025c143bc147f9cfd78f.json",
					"name" : "gmock",
					"projectIndex" : 2
				},
				{
					"directoryIndex" : 2,
					"id" : "gmock_main::@d68da25237a7ca2351af",
					"jsonFile" : "target-gmock_main-RelWithDebInfo-7cb68220aa975acda979.json",
					"name" : "gmock_main",
					"projectIndex" : 2
				},
				{
					"directoryIndex" : 3,
					"id" : "gtest::@f95b5c00bd49b3b4698d",
					"jsonFile" : "target-gtest-RelWithDebInfo-a50856537aa459fa5c8e.json",
					"name" : "gtest",
					"projectIndex" : 3
				},
				{
					"directoryIndex" : 3,
					"id" : "gtest_main::@f95b5c00bd49b3b4698d",
					"jsonFile" : "target-gtest_main-RelWithDebInfo-0bb00db3e5f787157312.json",
					"name" : "gtest_main",
					"projectIndex" : 3
				},
				{
					"directoryIndex" : 0,
					"id" : "my_tests::@6890427a1f51a3e7e1df",
					"jsonFile" : "target-my_tests-RelWithDebInfo-313cbc40da6c9dad9a44.json",
					"name" : "my_tests",
					"projectIndex" : 0
				}
			]
		}
	],
	"kind" : "codemodel",
	"paths" : 
	{
		"build" : "C:/Users/t.zaman/Desktop/workspace/gtest/gtest02/source/build",
		"source" : "C:/Users/t.zaman/Desktop/workspace/gtest/gtest02/source"
	},
	"version" : 
	{
		"major" : 2,
		"minor" : 5
	}
}
